based/__init__.py
based/metric.py
based/model/based_random_forest.joblib
based_metric-0.0.3.dist-info/METADATA
based_metric-0.0.3.dist-info/WHEEL
based_metric-0.0.3.dist-info/top_level.txt
based_metric-0.0.3.dist-info/RECORD
