Metadata-Version: 2.1
Name: based-metric
Version: 0.0.3
Summary: BASED metric for deblurring assesement
Home-page: 
Author: Nick Alutis
Author-email: 
Classifier: Programming Language :: Python
Classifier: Programming Language :: Python :: 3
Classifier: Programming Language :: Python :: 3.9
Requires-Dist: numpy
Requires-Dist: lpips
Requires-Dist: torchsummary
Requires-Dist: opencv-contrib-python
Requires-Dist: opencv-python
Requires-Dist: pandas
Requires-Dist: scikit-image
Requires-Dist: scikit-learn
Requires-Dist: matplotlib
Requires-Dist: seaborn
Requires-Dist: scipy
Requires-Dist: pathos
Requires-Dist: tqdm
